orthohmm/__init__.py
orthohmm/__main__.py
orthohmm/args_processing.py
orthohmm/externals.py
orthohmm/files.py
orthohmm/helpers.py
orthohmm/orthohmm.py
orthohmm/parser.py
orthohmm/version.py
orthohmm/writer.py
orthohmm-0.1.1.dist-info/LICENSE.md
orthohmm-0.1.1.dist-info/METADATA
orthohmm-0.1.1.dist-info/WHEEL
orthohmm-0.1.1.dist-info/entry_points.txt
orthohmm-0.1.1.dist-info/top_level.txt
orthohmm-0.1.1.dist-info/RECORD
