Metadata-Version: 2.1
Name: orthohmm
Version: 0.1.1
Summary: HMM-based orthogroups
Home-page: https://github.com/jlsteenwyk/orthohmm
Author: Jacob L. Steenwyk
Author-email: jlsteenwyk@gmail.com
Classifier: Operating System :: OS Independent
Classifier: Intended Audience :: Science/Research
Classifier: Programming Language :: Python
Classifier: Programming Language :: Python :: 3.9
Classifier: Programming Language :: Python :: 3.10
Classifier: Programming Language :: Python :: 3.11
Classifier: Topic :: Scientific/Engineering
License-File: LICENSE.md
Requires-Dist: numpy>=2.0.1
Requires-Dist: cython
